eightstars/__init__.py
eightstars/geometry.py
eight_stars-1.0.0.dist-info/LICENSE
eight_stars-1.0.0.dist-info/METADATA
eight_stars-1.0.0.dist-info/WHEEL
eight_stars-1.0.0.dist-info/top_level.txt
eight_stars-1.0.0.dist-info/RECORD
