Metadata-Version: 2.1
Name: eight-stars
Version: 1.0.0
Summary: Simple stars geometries
Home-page: https://github.com/rganowski/eight-stars
Author: Robert Ganowski
Author-email: robert.ganowski@gmail.com
License: MIT
Platform: Posix; MacOS X; Windows
Classifier: Programming Language :: Python :: 3.7
Classifier: License :: OSI Approved :: MIT License
Classifier: Operating System :: OS Independent
Requires-Python: >=3.7
